MANIFEST.in
README.rst
setup.py
nullsmtp/__init__.py
nullsmtp/logger.py
nullsmtp/nullsmtp.py
nullsmtp.egg-info/PKG-INFO
nullsmtp.egg-info/SOURCES.txt
nullsmtp.egg-info/dependency_links.txt
nullsmtp.egg-info/entry_points.txt
nullsmtp.egg-info/top_level.txt