Metadata-Version: 1.1
Name: nullsmtp
Version: 0.3.0
Summary: Fake SMTP server
Home-page: http://github.com/MasterOdin/nullsmtp
Author: Matthew Peveler
Author-email: matt.peveler@gmail.com
License: UNKNOWN
Platform: UNKNOWN
Classifier: Development Status :: 5 - Production/Stable
Classifier: Programming Language :: Python
Classifier: Programming Language :: Python :: 3 :: Only
Classifier: Environment :: Console
Classifier: Intended Audience :: Developers
Classifier: Intended Audience :: Information Technology
Classifier: License :: Public Domain
Classifier: Topic :: Communications :: Email :: Mail Transport Agents
